<?xml version="1.0" encoding="ISO-8859-1" ?> 
<!-- Copyright 2004 Rockwell Automation --> 
<LogixController> 
    <Name>"ControlLogix5561"</Name>
	<SchemaVersion>
        <Major>1</Major>
        <Minor>3</Minor>
    </SchemaVersion>
	<DeviceIdentities>
		<DeviceIdentity Instance="1">
			<VendorID>1</VendorID>
			<ProductType>14</ProductType>
			<ProductCode>54</ProductCode> 
			<MajorRevision>1</MajorRevision>
			<MinorRevision>1</MinorRevision>
            <SubminorRevision>1</SubminorRevision>
			<ProductNameString>1756-L61/B </ProductNameString>
			<ACproductNameString>LOGIX5561</ACproductNameString>
            <HWMajorRevision>2</HWMajorRevision>
            <HWMinorRevision>1</HWMinorRevision>
		</DeviceIdentity>
	</DeviceIdentities> 
	<UserDTMemorySize>2097152</UserDTMemorySize>
	<UserIOMemorySize>505856</UserIOMemorySize>
</LogixController>
